AUTHORS
LICENSE
MANIFEST.in
README.rst
setup.py
django_formwizard.egg-info/PKG-INFO
django_formwizard.egg-info/SOURCES.txt
django_formwizard.egg-info/dependency_links.txt
django_formwizard.egg-info/not-zip-safe
django_formwizard.egg-info/top_level.txt
docs/gettingstarted.rst
docs/index.rst
formwizard/__init__.py
formwizard/compat.py
formwizard/forms.py
formwizard/models.py
formwizard/views.py
formwizard/storage/__init__.py
formwizard/storage/base.py
formwizard/storage/cookie.py
formwizard/storage/exceptions.py
formwizard/storage/session.py
formwizard/templates/formwizard/wizard_form.html
formwizard/tests/__init__.py
formwizard/tests/cookiestoragetests.py
formwizard/tests/formtests.py
formwizard/tests/loadstoragetests.py
formwizard/tests/sessionstoragetests.py
formwizard/tests/storagetests.py
formwizard/tests/namedwizardtests/__init__.py
formwizard/tests/namedwizardtests/forms.py
formwizard/tests/namedwizardtests/tests.py
formwizard/tests/namedwizardtests/urls.py
formwizard/tests/wizardtests/__init__.py
formwizard/tests/wizardtests/forms.py
formwizard/tests/wizardtests/tests.py
formwizard/tests/wizardtests/urls.py
formwizard/tests/wizardtests/templates/other_wizard_form.html