Metadata-Version: 1.0
Name: django-formwizard
Version: 1.0
Summary: A FormWizard for Django with multiple storage backends
Home-page: http://github.com/stephrdev/django-formwizard/
Author: Stephan Jaekel
Author-email: steph@rdev.info
License: UNKNOWN
Platform: UNKNOWN
Classifier: Development Status :: 4 - Beta
Classifier: Environment :: Web Environment
Classifier: Intended Audience :: Developers
Classifier: License :: OSI Approved :: BSD License
Classifier: Operating System :: OS Independent
Classifier: Programming Language :: Python
Classifier: Framework :: Django
